inception_db_connect/__init__.py
inception_db_connect/es_connect.py
inception_db_connect/helper.py
inception_db_connect/mongo_connect.py
inception_db_connect/pg_connect.py
inception_db_connect/settings_db_connect.py
inception_db_connect-0.2.5.dist-info/LICENSE
inception_db_connect-0.2.5.dist-info/METADATA
inception_db_connect-0.2.5.dist-info/WHEEL
inception_db_connect-0.2.5.dist-info/top_level.txt
inception_db_connect-0.2.5.dist-info/RECORD
