Metadata-Version: 2.1
Name: inception_db_connect
Version: 0.2.5
Summary: inception_db_connect is a package that allows you to connect to a database
Home-page: https://github.com/KhaduaBloom/inceptionforcepackages/tree/main/PythonPackage/inceptionDBConnect
Author: KhaduaBloom
Author-email: khaduabloom@gmail.com
Classifier: Programming Language :: Python :: 3
Classifier: License :: OSI Approved :: MIT License
Classifier: Operating System :: OS Independent
Requires-Python: >=3.13.0
License-File: LICENSE
Requires-Dist: graypy==2.1.0
Requires-Dist: psutil==6.1.0
Requires-Dist: fastapi
Requires-Dist: uvicorn
Requires-Dist: pydantic-settings
Requires-Dist: sqlalchemy
Requires-Dist: pymongo[srv]
Requires-Dist: elasticsearch==8.17.2
Requires-Dist: opensearch-py
Requires-Dist: requests-aws4auth
Requires-Dist: boto3
